yodi/Yodi.py
yodi/__init__.py
yodipacks-0.3.1.dist-info/LICENSE
yodipacks-0.3.1.dist-info/METADATA
yodipacks-0.3.1.dist-info/WHEEL
yodipacks-0.3.1.dist-info/top_level.txt
yodipacks-0.3.1.dist-info/RECORD
