Metadata-Version: 2.1
Name: yodipacks
Version: 0.3.1
License-File: LICENSE
